jenkins/__init__.py
jenkins/_version.py
jenkins/compat.py
jenkins/utils/__init__.py
jenkins/utils/secret/__init__.py
jenkins/utils/secret/__main__.py
tests/__init__.py
tests/test_utils_secret.py
jenkins_utils-0.1.2.dist-info/METADATA
jenkins_utils-0.1.2.dist-info/WHEEL
jenkins_utils-0.1.2.dist-info/entry_points.txt
jenkins_utils-0.1.2.dist-info/top_level.txt
jenkins_utils-0.1.2.dist-info/RECORD
