Metadata-Version: 2.1
Name: jenkins-utils
Version: 0.1.2
Summary: Jenkins Utils
Home-page: https://github.com/tarvitz/jenkins-secret
Author: Nickolas Fox
Author-email: tarvitz@blacklibrary.ru
License: UNKNOWN
Keywords: jenkins cipher secret tools utils aes ecb cbc
Platform: any
Classifier: Development Status :: 4 - Beta
Classifier: Environment :: Other Environment
Classifier: Intended Audience :: Developers
Classifier: License :: OSI Approved :: BSD License
Classifier: Operating System :: POSIX
Classifier: Programming Language :: Python :: 3.4
Classifier: Programming Language :: Python :: 3.5
Classifier: Programming Language :: Python :: 3.6
Classifier: Programming Language :: Python :: 3.7
Classifier: Programming Language :: Python :: 3 :: Only
Classifier: Programming Language :: Python :: Implementation :: CPython
Classifier: Topic :: Software Development :: Libraries
Requires-Python: >=3
Requires-Dist: pycrypto (>=2.6.1) ; platform_system != "Windows"
Requires-Dist: pycryptodomex (>=3.6.1) ; platform_system == "Windows"
